gmplot/__init__.py
gmplot/color.py
gmplot/gmplot.py
gmplot/google_maps_templates.py
gmplot/utility.py
gmplot/writer.py
gmplot/markers/000000.png
gmplot/markers/000080.png
gmplot/markers/00008B.png
gmplot/markers/0000CD.png
gmplot/markers/0000FF.png
gmplot/markers/006400.png
gmplot/markers/008000.png
gmplot/markers/008080.png
gmplot/markers/008B8B.png
gmplot/markers/00BFFF.png
gmplot/markers/00CED1.png
gmplot/markers/00FA9A.png
gmplot/markers/00FF00.png
gmplot/markers/00FF7F.png
gmplot/markers/00FFFF.png
gmplot/markers/191970.png
gmplot/markers/1E90FF.png
gmplot/markers/20B2AA.png
gmplot/markers/228B22.png
gmplot/markers/2E8B57.png
gmplot/markers/2F4F4F.png
gmplot/markers/32CD32.png
gmplot/markers/3CB371.png
gmplot/markers/40E0D0.png
gmplot/markers/4169E1.png
gmplot/markers/4682B4.png
gmplot/markers/483D8B.png
gmplot/markers/48D1CC.png
gmplot/markers/4B0082.png
gmplot/markers/556B2F.png
gmplot/markers/5F9EA0.png
gmplot/markers/6495ED.png
gmplot/markers/66CDAA.png
gmplot/markers/696969.png
gmplot/markers/6A5ACD.png
gmplot/markers/6B8E23.png
gmplot/markers/708090.png
gmplot/markers/778899.png
gmplot/markers/7B68EE.png
gmplot/markers/7CFC00.png
gmplot/markers/7FFF00.png
gmplot/markers/7FFFD4.png
gmplot/markers/800000.png
gmplot/markers/800080.png
gmplot/markers/808000.png
gmplot/markers/808080.png
gmplot/markers/87CEEB.png
gmplot/markers/87CEFA.png
gmplot/markers/8A2BE2.png
gmplot/markers/8B0000.png
gmplot/markers/8B008B.png
gmplot/markers/8B4513.png
gmplot/markers/8FBC8F.png
gmplot/markers/90EE90.png
gmplot/markers/9370DB.png
gmplot/markers/9400D3.png
gmplot/markers/98FB98.png
gmplot/markers/9932CC.png
gmplot/markers/9ACD32.png
gmplot/markers/A0522D.png
gmplot/markers/A52A2A.png
gmplot/markers/A9A9A9.png
gmplot/markers/ADD8E6.png
gmplot/markers/ADFF2F.png
gmplot/markers/AFEEEE.png
gmplot/markers/B0C4DE.png
gmplot/markers/B0E0E6.png
gmplot/markers/B22222.png
gmplot/markers/B8860B.png
gmplot/markers/BA55D3.png
gmplot/markers/BC8F8F.png
gmplot/markers/BDB76B.png
gmplot-1.4.0.dist-info/LICENSE
gmplot-1.4.0.dist-info/METADATA
gmplot-1.4.0.dist-info/WHEEL
gmplot-1.4.0.dist-info/top_level.txt
gmplot-1.4.0.dist-info/RECORD
