Metadata-Version: 2.1
Name: gmplot
Version: 1.4.0
Summary: A matplotlib-like interface to plot data with Google Maps.
Home-page: https://github.com/gmplot/gmplot
Author: gmplot contributors
Author-email: UNKNOWN
License: MIT
Keywords: python google-maps visualization
Platform: UNKNOWN
Requires-Dist: requests
